exp2/exp2.srcs/sources_1/new/regfile.v
module regfile(
  input         clk,
  input  [ 4:0] raddr1,
  output [31:0] rdata1,
  input  [ 4:0] raddr2,
  output [31:0] rdata2,
  input         we,
  input  [ 4:0] waddr,
  input  [31:0] wdata
);
// Initial
reg [31:0] rf[31:0];
integer i;
initial 
    begin
        for(i=0; i<32; i=i+1)
            rf[i] = 0;
    end
// WRITE
always @(posedge clk) begin
    if (we) rf[waddr]<= wdata;
end
// READ OUT 1
assign rdata1 = (raddr1==5'b0) ? 32'b0 : rf[raddr1];
// READ OUT 2
assign rdata2 = (raddr2==5'b0) ? 32'b0 : rf[raddr2];
endmodule

exp2/exp2.srcs/sim_1/new/rf_tb.v
`timescale 1ns / 1ps

module tb_top();

reg         clk;

reg  [ 4:0] raddr1;
wire [31:0] rdata1;
reg  [ 4:0] raddr2;
wire [31:0] rdata2;
reg         we;
reg  [ 4:0] waddr;
reg  [31:0] wdata;

reg  [ 3:0] task_phase;

regfile u_regfile(
    .clk      (clk       ),
    .raddr1   (raddr1    ),
    .rdata1   (rdata1    ),
    .raddr2   (raddr2    ),
    .rdata2   (rdata2    ),
    .we       (we        ),
    .waddr    (waddr     ),
    .wdata    (wdata     ) 
);

//clk
initial 
begin
    clk = 1'b1;
end
always #5 clk = ~clk;
					
initial 
begin
    raddr1 =  5'd0;
    raddr2 =  5'd0;
	waddr  =  5'd0;
	wdata  = 32'd0;
	we     =  1'd0;
	task_phase =  4'd0;
	#2000;
	
	$display("=============================");
	$display("Test Begin");
	#1;
	// Part 0 Begin
	#10;
	task_phase = 4'd0;
	we         = 1'b0;
	waddr      = 5'd1;
	wdata      = 32'hffffffff;
    raddr1     = 5'd1;
    #10;
	we         = 1'b1;
	waddr      = 5'd1;
	wdata      = 32'h1111ffff;
    #10;
	we         = 1'b0;
    raddr1     = 5'd2;
    raddr2     = 5'd1;
	#10;
    raddr1     = 5'd1;
    
    #200;
    // Part 1 Begin
    #10;
	task_phase = 4'd1;
	we         = 1'b1;
	wdata      = 32'h0000ffff;
	waddr      =  5'h10;
    raddr1     =  5'h10;
    raddr2     =  5'h0f;
	#10;
	wdata      = 32'h1111ffff;
	waddr      =  5'h11;
    raddr1     =  5'h11;
    raddr2     =  5'h10;
	#10;
	wdata      = 32'h2222ffff;
	waddr      =  5'h12;
    raddr1     =  5'h12;
    raddr2     =  5'h11;
	#10;
	wdata      = 32'h3333ffff;
	waddr      =  5'h13;
    raddr1     =  5'h13;
    raddr2     =  5'h12;
	#10;
	wdata      = 32'h4444ffff;
	waddr      =  5'h14;
    raddr1     =  5'h14;
    raddr2     =  5'h13;
	#10;
    raddr1     =  5'h15;
    raddr2     =  5'h14;
	#10;

    #200;
	// Part 2 Begin
	#10;
	task_phase = 4'd2;
	we         = 1'b1;
    raddr1     =  5'h10;
    raddr2     =  5'h0f;
	#10;
    raddr1     =  5'h11;
    raddr2     =  5'h10;
	#10;
    raddr1     =  5'h12;
    raddr2     =  5'h11;
	#10;
    raddr1     =  5'h13;
    raddr2     =  5'h12;
	#10;
    raddr1     =  5'h14;
    raddr2     =  5'h13;
	#10;
	
	#50;
	$display("TEST END");
	$finish;
end

// 工作目录下生成仿真波形文件并保存
	initial begin
		$dumpfile("rf.vcd");
		$dumpvars(0, u_regfile); 
	end

endmodule

exp2/exp2.sim/sim_1/behav/xsim/rf.vcd
$date
   Fri Oct 31 18:17:26 2025
$end
$version
  2022.2
$end
$timescale
  1ps
$end
$scope module tb_top $end
$scope module u_regfile $end
$var wire 1 ! clk $end
$var wire 5 " raddr1 [4:0] $end
$var wire 32 # rdata1 [31:0] $end
$var wire 5 $ raddr2 [4:0] $end
$var wire 32 % rdata2 [31:0] $end
$var wire 1 & we $end
$var wire 5 ' waddr [4:0] $end
$var wire 32 ( wdata [31:0] $end
$var integer 32 ) i [31:0] $end
$upscope $end
$upscope $end
$enddefinitions $end
#0
$dumpvars
1!
b0 "
b0 #
b0 $
b0 %
0&
b0 '
b0 (
b100000 )
$end
#5000
0!
#10000
1!
#15000
0!
#20000
1!
#25000
0!
#30000
1!
#35000
0!
#40000
1!
#45000
0!
#50000
1!
#55000
0!
#60000
1!
#65000
0!
#70000
1!
#75000
0!
#80000
1!
#85000
0!
#90000
1!
#95000
0!
#100000
1!
#105000
0!
#110000
1!
#115000
0!
#120000
1!
#125000
0!
#130000
1!
#135000
0!
#140000
1!
#145000
0!
#150000
1!
#155000
0!
#160000
1!
#165000
0!
#170000
1!
#175000
0!
#180000
1!
#185000
0!
#190000
1!
#195000
0!
#200000
1!
#205000
0!
#210000
1!
#215000
0!
#220000
1!
#225000
0!
#230000
1!
#235000
0!
#240000
1!
#245000
0!
#250000
1!
#255000
0!
#260000
1!
#265000
0!
#270000
1!
#275000
0!
#280000
1!
#285000
0!
#290000
1!
#295000
0!
#300000
1!
#305000
0!
#310000
1!
#315000
0!
#320000
1!
#325000
0!
#330000
1!
#335000
0!
#340000
1!
#345000
0!
#350000
1!
#355000
0!
#360000
1!
#365000
0!
#370000
1!
#375000
0!
#380000
1!
#385000
0!
#390000
1!
#395000
0!
#400000
1!
#405000
0!
#410000
1!
#415000
0!
#420000
1!
#425000
0!
#430000
1!
#435000
0!
#440000
1!
#445000
0!
#450000
1!
#455000
0!
#460000
1!
#465000
0!
#470000
1!
#475000
0!
#480000
1!
#485000
0!
#490000
1!
#495000
0!
#500000
1!
#505000
0!
#510000
1!
#515000
0!
#520000
1!
#525000
0!
#530000
1!
#535000
0!
#540000
1!
#545000
0!
#550000
1!
#555000
0!
#560000
1!
#565000
0!
#570000
1!
#575000
0!
#580000
1!
#585000
0!
#590000
1!
#595000
0!
#600000
1!
#605000
0!
#610000
1!
#615000
0!
#620000
1!
#625000
0!
#630000
1!
#635000
0!
#640000
1!
#645000
0!
#650000
1!
#655000
0!
#660000
1!
#665000
0!
#670000
1!
#675000
0!
#680000
1!
#685000
0!
#690000
1!
#695000
0!
#700000
1!
#705000
0!
#710000
1!
#715000
0!
#720000
1!
#725000
0!
#730000
1!
#735000
0!
#740000
1!
#745000
0!
#750000
1!
#755000
0!
#760000
1!
#765000
0!
#770000
1!
#775000
0!
#780000
1!
#785000
0!
#790000
1!
#795000
0!
#800000
1!
#805000
0!
#810000
1!
#815000
0!
#820000
1!
#825000
0!
#830000
1!
#835000
0!
#840000
1!
#845000
0!
#850000
1!
#855000
0!
#860000
1!
#865000
0!
#870000
1!
#875000
0!
#880000
1!
#885000
0!
#890000
1!
#895000
0!
#900000
1!
#905000
0!
#910000
1!
#915000
0!
#920000
1!
#925000
0!
#930000
1!
#935000
0!
#940000
1!
#945000
0!
#950000
1!
#955000
0!
#960000
1!
#965000
0!
#970000
1!
#975000
0!
#980000
1!
#985000
0!
#990000
1!
#995000
0!
#1000000
1!
#1005000
0!
#1010000
1!
#1015000
0!
#1020000
1!
#1025000
0!
#1030000
1!
#1035000
0!
#1040000
1!
#1045000
0!
#1050000
1!
#1055000
0!
#1060000
1!
#1065000
0!
#1070000
1!
#1075000
0!
#1080000
1!
#1085000
0!
#1090000
1!
#1095000
0!
#1100000
1!
#1105000
0!
#1110000
1!
#1115000
0!
#1120000
1!
#1125000
0!
#1130000
1!
#1135000
0!
#1140000
1!
#1145000
0!
#1150000
1!
#1155000
0!
#1160000
1!
#1165000
0!
#1170000
1!
#1175000
0!
#1180000
1!
#1185000
0!
#1190000
1!
#1195000
0!
#1200000
1!
#1205000
0!
#1210000
1!
#1215000
0!
#1220000
1!
#1225000
0!
#1230000
1!
#1235000
0!
#1240000
1!
#1245000
0!
#1250000
1!
#1255000
0!
#1260000
1!
#1265000
0!
#1270000
1!
#1275000
0!
#1280000
1!
#1285000
0!
#1290000
1!
#1295000
0!
#1300000
1!
#1305000
0!
#1310000
1!
#1315000
0!
#1320000
1!
#1325000
0!
#1330000
1!
#1335000
0!
#1340000
1!
#1345000
0!
#1350000
1!
#1355000
0!
#1360000
1!
#1365000
0!
#1370000
1!
#1375000
0!
#1380000
1!
#1385000
0!
#1390000
1!
#1395000
0!
#1400000
1!
#1405000
0!
#1410000
1!
#1415000
0!
#1420000
1!
#1425000
0!
#1430000
1!
#1435000
0!
#1440000
1!
#1445000
0!
#1450000
1!
#1455000
0!
#1460000
1!
#1465000
0!
#1470000
1!
#1475000
0!
#1480000
1!
#1485000
0!
#1490000
1!
#1495000
0!
#1500000
1!
#1505000
0!
#1510000
1!
#1515000
0!
#1520000
1!
#1525000
0!
#1530000
1!
#1535000
0!
#1540000
1!
#1545000
0!
#1550000
1!
#1555000
0!
#1560000
1!
#1565000
0!
#1570000
1!
#1575000
0!
#1580000
1!
#1585000
0!
#1590000
1!
#1595000
0!
#1600000
1!
#1605000
0!
#1610000
1!
#1615000
0!
#1620000
1!
#1625000
0!
#1630000
1!
#1635000
0!
#1640000
1!
#1645000
0!
#1650000
1!
#1655000
0!
#1660000
1!
#1665000
0!
#1670000
1!
#1675000
0!
#1680000
1!
#1685000
0!
#1690000
1!
#1695000
0!
#1700000
1!
#1705000
0!
#1710000
1!
#1715000
0!
#1720000
1!
#1725000
0!
#1730000
1!
#1735000
0!
#1740000
1!
#1745000
0!
#1750000
1!
#1755000
0!
#1760000
1!
#1765000
0!
#1770000
1!
#1775000
0!
#1780000
1!
#1785000
0!
#1790000
1!
#1795000
0!
#1800000
1!
#1805000
0!
#1810000
1!
#1815000
0!
#1820000
1!
#1825000
0!
#1830000
1!
#1835000
0!
#1840000
1!
#1845000
0!
#1850000
1!
#1855000
0!
#1860000
1!
#1865000
0!
#1870000
1!
#1875000
0!
#1880000
1!
#1885000
0!
#1890000
1!
#1895000
0!
#1900000
1!
#1905000
0!
#1910000
1!
#1915000
0!
#1920000
1!
#1925000
0!
#1930000
1!
#1935000
0!
#1940000
1!
#1945000
0!
#1950000
1!
#1955000
0!
#1960000
1!
#1965000
0!
#1970000
1!
#1975000
0!
#1980000
1!
#1985000
0!
#1990000
1!
#1995000
0!
#2000000
1!
#2005000
0!
#2010000
1!
#2011000
b1 "
b1 '
b11111111111111111111111111111111 (
#2015000
0!
#2020000
1!
#2021000
1&
b10001000100011111111111111111 (
#2025000
0!
#2030000
1!
b10001000100011111111111111111 #
#2031000
b10 "
b0 #
b1 $
b10001000100011111111111111111 %
0&
#2035000
0!
#2040000
1!
#2041000
b1 "
b10001000100011111111111111111 #
#2045000
0!
#2050000
1!
#2055000
0!
#2060000
1!
#2065000
0!
#2070000
1!
#2075000
0!
#2080000
1!
#2085000
0!
#2090000
1!
#2095000
0!
#2100000
1!
#2105000
0!
#2110000
1!
#2115000
0!
#2120000
1!
#2125000
0!
#2130000
1!
#2135000
0!
#2140000
1!
#2145000
0!
#2150000
1!
#2155000
0!
#2160000
1!
#2165000
0!
#2170000
1!
#2175000
0!
#2180000
1!
#2185000
0!
#2190000
1!
#2195000
0!
#2200000
1!
#2205000
0!
#2210000
1!
#2215000
0!
#2220000
1!
#2225000
0!
#2230000
1!
#2235000
0!
#2240000
1!
#2245000
0!
#2250000
1!
#2251000
b10000 "
b0 #
b1111 $
b0 %
1&
b10000 '
b1111111111111111 (
#2255000
0!
#2260000
1!
b1111111111111111 #
#2261000
b10001 "
b0 #
b10000 $
b1111111111111111 %
b10001 '
b10001000100011111111111111111 (
#2265000
0!
#2270000
1!
b10001000100011111111111111111 #
#2271000
b10010 "
b0 #
b10001 $
b10001000100011111111111111111 %
b10010 '
b100010001000101111111111111111 (
#2275000
0!
#2280000
1!
b100010001000101111111111111111 #
#2281000
b10011 "
b0 #
b10010 $
b100010001000101111111111111111 %
b10011 '
b110011001100111111111111111111 (
#2285000
0!
#2290000
1!
b110011001100111111111111111111 #
#2291000
b10100 "
b0 #
b10011 $
b110011001100111111111111111111 %
b10100 '
b1000100010001001111111111111111 (
#2295000
0!
#2300000
1!
b1000100010001001111111111111111 #
#2301000
b10101 "
b0 #
b10100 $
b1000100010001001111111111111111 %
